dlorg.py
dlorg-2.3.dist-info/LICENSE
dlorg-2.3.dist-info/METADATA
dlorg-2.3.dist-info/WHEEL
dlorg-2.3.dist-info/entry_points.txt
dlorg-2.3.dist-info/RECORD
