Metadata-Version: 2.1
Name: dlorg
Version: 2.3
Summary: A Python script to organize your downloads folder by file extensions and mimetypes.
Home-page: https://github.com/at-pyrix/download-organizer
License: GPL-3.0
Author: pyrix
Author-email: probablynotyasho@gmail.com
Requires-Python: >=3.6,<4.0
Classifier: License :: OSI Approved :: GNU General Public License v3 (GPLv3)
Classifier: Programming Language :: Python :: 3
Classifier: Programming Language :: Python :: 3.6
Classifier: Programming Language :: Python :: 3.7
Classifier: Programming Language :: Python :: 3.8
Classifier: Programming Language :: Python :: 3.9
Classifier: Programming Language :: Python :: 3.10
Classifier: Programming Language :: Python :: 3.11
Classifier: Programming Language :: Python :: 3.12
Requires-Dist: colorama (>=0.4.4,<0.5.0)
Requires-Dist: python-magic (>=0.4.27,<0.5.0)
Project-URL: Repository, https://github.com/at-pyrix/download-organizer
